{
  "lastUpdated": "2026-07-09T13:45:35.029395+00:00",
  "totalSources": 3,
  "totalNews": 30,
  "news": [
    {
      "title": "Edicioni i gjashtë i Porto Palermo Festival",
      "link": "https://24-ore.com/edicioni-i-gjashte-i-porto-palermo-festival/",
      "description": "Edhe këtë verë Porto Palermo Festival do të sjellë një program të pasur artistik në Rivierën shqiptare. Nga data 30 korrik e deri më 16 gusht, ideatori i këtij festivali, Olen Cesari, ka programuar 12 net të magjishme në kalanë e Porto Palermos. Ky do të jetë edicioni i 6-të i Porto Palermo Festival",
      "source": "24 ORE",
      "category": "politike",
      "date": "2026-07-09T13:45:24+00:00",
      "dateStr": "09 Jul, 13:45",
      "isNew": true,
      "id": "24 01783604724"
    },
    {
      "title": "Gjermania nënshkruan marrëveshje me SHBA-në për blerjen dhe vendosjen e raketave Tomahawk",
      "link": "https://24-ore.com/gjermania-nenshkruan-marreveshje-me-shba-ne-per-blerjen-dhe-vendosjen-e-raketave-tomahawk/",
      "description": "Kancelari Friedrich Merz njoftoi të enjten se Gjermania ka arritur një marrëveshje me Shtetet e Bashkuara për blerjen e raketave cruise me rreze të gjatë Tomahawk dhe vendosjen e tyre në territorin gjerman. Ai bëri me dije se marrëveshja u finalizua këtë javë ndërsa ai po merrte pjesë në samitin e N",
      "source": "24 ORE",
      "category": "politike",
      "date": "2026-07-09T13:44:39+00:00",
      "dateStr": "09 Jul, 13:44",
      "isNew": true,
      "id": "24 11783604679"
    },
    {
      "title": "Berisha: Rama në samitin e NATO, si njeriu i përçmuar",
      "link": "https://24-ore.com/berisha-rama-ne-samitin-e-nato-si-njeriu-i-percmuar/",
      "description": "Për kryedemokratin Berisha prej dy muajsh në qarqet ndërkombëtare qarkullojnë lajme që venë në pikëpyetje mbajtjen e samitit të NATOS-s në Tiranë vitin e ardhshëm. Edhe pse nuk pranoi të hyjë në këtë diskutim, Berisha në fjalën e tij çojë vëmendjen tek detajet të samitit që le të kuptohet se informa",
      "source": "24 ORE",
      "category": "politike",
      "date": "2026-07-09T13:42:07+00:00",
      "dateStr": "09 Jul, 13:42",
      "isNew": true,
      "id": "24 21783604527"
    },
    {
      "title": "Arrestohet në Himarë 38-vjeçari me precedent penal, lëvizte me pistoletë dhe granatë",
      "link": "https://24-ore.com/arrestohet-ne-himare-38-vjecari-me-precedent-penal-levizte-me-pistolete-dhe-granate/",
      "description": "Një 38-vjeçar me precedent penal për krime kundër personit është arrestuar në flagrancë nga Policia në Himarë, pasi u kap duke qarkulluar me automjet me armë zjarri dhe granatë. Në kuadër të operacionit të koduar “Siguria 2”, policia e Himarës, në bashkëpunim me Forcën e Posaçme “Shqiponja” të Vlorë",
      "source": "24 ORE",
      "category": "politike",
      "date": "2026-07-09T13:40:58+00:00",
      "dateStr": "09 Jul, 13:40",
      "isNew": true,
      "id": "24 31783604458"
    },
    {
      "title": "PD denoncon: Rama dhe Balluku po rrezikojnë sigurinë kombëtare me aferën KAYO",
      "link": "https://24-ore.com/pd-denoncon-rama-dhe-balluku-po-rrezikojne-sigurine-kombetare-me-aferen-kayo/",
      "description": "Partia Demokratike, përmes deputetit Klevis Balliu, akuzoi Kryeministrin Edi Rama dhe ish-zëvendës kryeministren Belinda Balluku si cenues të sigurisë kombëtare , përmes projektit sipas tij korruptiv KAYO. “Afera e Kajos nuk është më thjeshtë një çështje e Ministrisë së Mbrojtjes. Ajo është një afer",
      "source": "24 ORE",
      "category": "politike",
      "date": "2026-07-09T13:37:31+00:00",
      "dateStr": "09 Jul, 13:37",
      "isNew": true,
      "id": "24 41783604251"
    },
    {
      "title": "​A do të shkarkohet Abdixhiku, flasin anëtarë të Kryesisë së LDK-së",
      "link": "https://24-ore.com/a-do-te-shkarkohet-abdixhiku-flasin-anetare-te-kryesise-se-ldk-se/",
      "description": "Nënkryetarja e Lidhjes Demokratike të Kosovës, Jehona Lushaku, tha se nuk është e përfshirë në nënshkrimet për shkarkimin e kryetarit të kësaj partie Lumir Abdixhiku. Para mbledhjes së Kryesisë të LDK-së, Lushaku e quajti LDK-në shembull të të gjitha partive dhe sipas saj duhet të ketë dialog të bre",
      "source": "24 ORE",
      "category": "politike",
      "date": "2026-07-09T13:32:48+00:00",
      "dateStr": "09 Jul, 13:32",
      "isNew": true,
      "id": "24 51783603968"
    },
    {
      "title": "Zyrtare: Albion Rrahmani transferohet te Venezia, firmos deri në vitin 2029",
      "link": "https://24-ore.com/zyrtare-albion-rrahmani-transferohet-te-venezia-firmos-deri-ne-vitin-2029/",
      "description": "Skip to content Categories Botërori 2026 E-sports Euro 2024 Ndërkombëtar Opinione Post Qatar 2022 Showbizz Sporte tjera Top Ligat Top Tema Trending Uncategorized Vendor July 2026 M T W T F S S   1 2 3 4 5 6 7 8 9 10 11 12 13 14 15 16 17 18 19 20 21 [&#8230;]",
      "source": "24 ORE",
      "category": "politike",
      "date": "2026-07-09T13:31:29+00:00",
      "dateStr": "09 Jul, 13:31",
      "isNew": true,
      "id": "24 61783603889"
    },
    {
      "title": "BOTËRORI 2026 – Edhe Justin Bieber i bashkohet spektaklit të finales",
      "link": "https://24-ore.com/boterori-2026-edhe-justin-bieber-i-bashkohet-spektaklit-te-finales/",
      "description": "– Ylli kanadez i muzikës pop Justin Bieber do të jetë pjesë e spektaklit të pjesës së parë të finales së Kupës së Botës 2026, duke iu bashkuar një liste emrash të mëdhenj të muzikës botërore, sipas Reuters. Sipas njoftimit, Bieber do të performojë së bashku me Madonnën, Shakirën dhe grupin koreanoju",
      "source": "24 ORE",
      "category": "politike",
      "date": "2026-07-09T13:30:28+00:00",
      "dateStr": "09 Jul, 13:30",
      "isNew": true,
      "id": "24 71783603828"
    },
    {
      "title": "Kupa e Botës 2026: Tani lindin legjendat",
      "link": "https://24-ore.com/kupa-e-botes-2026-tani-lindin-legjendat/",
      "description": "Turneu ka hyrë në fazën vendimtare: në mesin e tetë skuadrave më të mira janë ende gjashtë nga ato të renditura më lart në listën e FIFA-s, dhe semifinalet nisën të premten. Përballjet e ardhshme premtuan të vendosin jo vetëm fituesit e ndeshjeve, por edhe emrat që do të mbeten në histori. Raporton ",
      "source": "24 ORE",
      "category": "politike",
      "date": "2026-07-09T13:29:23+00:00",
      "dateStr": "09 Jul, 13:29",
      "isNew": true,
      "id": "24 81783603763"
    },
    {
      "title": "Bad Bunny vendos rekord në Emmy, spektakli i Super Bowl merr 9 nominime",
      "link": "https://24-ore.com/bad-bunny-vendos-rekord-ne-emmy-spektakli-i-super-bowl-merr-9-nominime/",
      "description": "Bad Bunny arrin një tjetër sukses të madh me paraqitjen e tij në Super Bowl LX. Performanca e artistit portorikan ka siguruar 9 kandidime për çmimet Emmy, duke u bërë halftime show me numrin më të lartë të vlerësimeve në historinë e këtij eventi. Një prej tyre është në kategorinë &#8220;Outstanding ",
      "source": "24 ORE",
      "category": "politike",
      "date": "2026-07-09T13:26:37+00:00",
      "dateStr": "09 Jul, 13:26",
      "isNew": true,
      "id": "24 91783603597"
    },
    {
      "title": "Integrimi, Shqipëria në çast vendimtar/ Pirdeni: Forcim i kapaciteteve dhe modernizim i administratës",
      "link": "https://abcnews.al/integrimi-shqiperia-ne-cast-vendimtar-pirdeni-forcim-i-kapaciteteve-dhe-modernizim-i-administrates/",
      "description": "Ministrja e Shtetit për Administratën Publike dhe Antikorrupsionin, Adea Pirdeni, në përmbyllje të Javës së Administratës, tha se Shqipëria ndodhet në një moment vendimtar për procesin e integrimit europian, ndërsa theksoi se anëtarësimi duhet parë si një mundësi për forcimin e shtetit dhe konsolidi",
      "source": "ABC News",
      "category": "politike",
      "date": "2026-07-09T13:15:07+00:00",
      "dateStr": "09 Jul, 13:15",
      "isNew": true,
      "id": "abc01783602907"
    },
    {
      "title": "Italia dëbon dy diplomatë rusë të akuzuar për spiunazh",
      "link": "https://abcnews.al/italia-debon-dy-diplomate-ruse-te-akuzuar-per-spiunazh/",
      "description": "Italia njoftoi sot dëbimin e dy agjentëve të shërbimeve sekrete ruse, të cilët ndodheshin në vend me status diplomatik. Qeveria italiane e cilësoi rastin si një “ndërhyrje të rëndë dhe të papranueshme”, vetëm dy ditë pasi u arrestuan dy ish-agjentë italianë të zbulimit të dyshuar për bashkëpunim me ",
      "source": "ABC News",
      "category": "politike",
      "date": "2026-07-09T13:10:17+00:00",
      "dateStr": "09 Jul, 13:10",
      "isNew": true,
      "id": "abc11783602617"
    },
    {
      "title": "Money Report me Genta Dobra, (09/07/2026)",
      "link": "https://abcnews.al/money-report-me-genta-dobra-09-07-2026/",
      "description": "[...]Read More...",
      "source": "ABC News",
      "category": "politike",
      "date": "2026-07-09T12:55:15+00:00",
      "dateStr": "09 Jul, 12:55",
      "isNew": true,
      "id": "abc21783601715"
    },
    {
      "title": "Shkodra magjeps australianët/ Shtohen vizitorët, të huajt vlerësojnë natyrën dhe atmosferën",
      "link": "https://abcnews.al/shkodra-magjeps-australianet-shtohen-vizitoret-te-huajt-vleresojne-natyren-dhe-atmosferen/",
      "description": "Shkodra, një qytet me gjallëri, ku sheshet e hapësirat e argëtimit janë të mbushura me vizitorë vendas e të huaj, ndërsa ata që kryesojnë këtë vit janë australianët. &#8220;Jam nga Melbourne, Australi.Më pëlqen shumë.Birra është e lirë.Ishim në Theth para disa ditësh dhe ishte e jashtëzakonshme.Notu",
      "source": "ABC News",
      "category": "politike",
      "date": "2026-07-09T12:51:57+00:00",
      "dateStr": "09 Jul, 12:51",
      "isNew": true,
      "id": "abc31783601517"
    },
    {
      "title": "FOTO/ Ekzekutoi gruan, ky është autori i dyshuar i krimit në Shkodër",
      "link": "https://abcnews.al/foto-ekzekutoi-gruan-ky-eshte-autori-i-dyshuar-i-krimit-ne-shkoder/",
      "description": "SHKODËR- Personi që shihni në foto është Shqefën Ziqi, i cili dyshohet se vrau me çifti ruan e tij Bardhe Ziqi. Sipas Policisë, ngjarja kriminale ndodhi në  lagjen “Mark Lula”, në qytetin e Shkodrës. Pas krimit, autori është arrestuar nga Policia. Trupi i pajetë i 55-vjeçares u gjet anës rrugës, ndë",
      "source": "ABC News",
      "category": "politike",
      "date": "2026-07-09T12:49:02+00:00",
      "dateStr": "09 Jul, 12:49",
      "isNew": true,
      "id": "abc41783601342"
    },
    {
      "title": "Plotësimi i gjyqtarëve në gjykata/ Kreu i KLGJ në Kuvend: Do të kryhet brenda vitit 2028",
      "link": "https://abcnews.al/plotesimi-i-gjyqtareve-ne-gjykata-kreu-i-klgj-ne-kuvend-do-te-kryhet-brenda-vitit-2028/",
      "description": "Këshilli i Lartë gjyqësor ka marrë masat e nevojshme për plotësimin e vakancave në sistemin gjyqësor deri në vitin 2028 tha Kryetari i Këshillit të Lartë Gjyqësor, Ilir Rusi gjatë raportimit në Komisionin për Nismat Qytetare, Bashkëpunimin dhe Mbikëqyrjen Institucionale &#8220;Janë marrë masat për p",
      "source": "ABC News",
      "category": "politike",
      "date": "2026-07-09T12:42:22+00:00",
      "dateStr": "09 Jul, 12:42",
      "isNew": true,
      "id": "abc51783600942"
    },
    {
      "title": "Europa, qershori më i nxehtë/ Mbi 4700 vdekje nga temperaturat e larta",
      "link": "https://abcnews.al/europa-qershori-me-i-nxehte-mbi-4700-vdekje-nga-temperaturat-e-larta/",
      "description": "Evropa Perëndimore ka përjetuar muajin qershor më të nxehtë të regjistruar ndonjëherë, sipas asaj që konfirmuan të enjten Shkencëtarët e Bashkimit Europian pas një vale të të nxehtit ekstrem në fund të muajit që theu rekorde temperaturash, shkaktoi ndërprerje të energjisë elektrike dhe çoi në mbyllj",
      "source": "ABC News",
      "category": "politike",
      "date": "2026-07-09T12:35:24+00:00",
      "dateStr": "09 Jul, 12:35",
      "isNew": true,
      "id": "abc61783600524"
    },
    {
      "title": "News Line me Rovena Neziri, (09/07/2026)",
      "link": "https://abcnews.al/news-line-me-rovena-neziri-09-07-2026/",
      "description": "[...]Read More...",
      "source": "ABC News",
      "category": "politike",
      "date": "2026-07-09T12:35:12+00:00",
      "dateStr": "09 Jul, 12:35",
      "isNew": true,
      "id": "abc71783600512"
    },
    {
      "title": "Europa, padrejtësi botërore/ Kontinenti i vjetër i pakënaqur me numrin e ekipeve në turne",
      "link": "https://abcnews.al/europa-padrejtesi-boterore-kontinenti-i-vjeter-i-pakenaqur-me-numrin-e-ekipeve-ne-turne/",
      "description": "Nëse thjesht sheh numrin të duket se i kanë bërë nder. Europa mbetet kontinenti me më shumë skuadra në Kupat e Botës, dhe në Amerikën e Veriut mbërriti me 16 të tilla. Pas saj është Afrika me 10 ekipe, gjë që reflekton rritjen e futbollit të atij që quhet “kontinenti I zi”, dhe në vendin [...]Read M",
      "source": "ABC News",
      "category": "politike",
      "date": "2026-07-09T12:32:38+00:00",
      "dateStr": "09 Jul, 12:32",
      "isNew": true,
      "id": "abc81783600358"
    },
    {
      "title": "Ramadani dyfishon rrogën/ Mesfushori kuqezi do të marrë 1.5 milionë euro në sezon",
      "link": "https://abcnews.al/ramadani-dyfishon-rrogen-mesfushori-kuqezi-do-te-marre-1-5-milione-euro-ne-sezon/",
      "description": "Ishte e habitshme kjo zgjedhje. Pas një Kristian Asllani që shkoi të paktën për një fazë, ja ku kemi edhe Ylber Ramadanin që braktis Serinë A të Italisë, një nga pesë ligat më të forta të Europës e të botës, për të shkuar në Dardanele. Mesfushori i kombëtares shqiptare zgjodhi një skuadër modeste të",
      "source": "ABC News",
      "category": "politike",
      "date": "2026-07-09T12:29:20+00:00",
      "dateStr": "09 Jul, 12:29",
      "isNew": true,
      "id": "abc91783600160"
    },
    {
      "title": "Rama kërkon mbledhje urgjente me deputetët e PS ditën e shtunë, zbulohet agjenda",
      "link": "https://www.lajme.al/rama-kerkon-mbledhje-urgjente-me-deputetet-e-ps-diten-e-shtune-zbulohet-agjenda/",
      "description": "Kryeministri Edi Rama pritet paraditen e së shtunës të drejtojë mbledhjen e Grupit Parlamentar të Partisë Socialiste, ku do të marrin pjesë edhe ministrat. Gazetari Muhamed Veliu ka zbuluar agjendën e kësaj mbledhjeje, të cilën do ta nisë kreu i Grupit, Taulant Balla, vijuar nga fjala e Kryeministri",
      "source": "Lajme.al",
      "category": "politike",
      "date": "2026-06-19T18:05:35+00:00",
      "dateStr": "19 Jun, 18:05",
      "isNew": false,
      "id": "laj01781892335"
    },
    {
      "title": "Lajme.al uron të gjithë besimtarët: Gëzuar Kurban Bajramin",
      "link": "https://www.lajme.al/lajme-al-uron-te-gjithe-besimtaret-gezuar-kurban-bajramin/",
      "description": "Urime festa e Kurban Bajramit! Gëzuar këtë festë të shenjtë dhe për shumë vite me paqe, shëndet e begati! Urojmë që kjo ditë e bekuar të sjellë qetësi në zemrat tona, harmoni në familje dhe dashuri mes njerëzve. Le të jetë një ditë që na afron më shumë me njëri-tjetrin, duke na kujtuar rëndësinë e [",
      "source": "Lajme.al",
      "category": "politike",
      "date": "2026-05-27T06:00:19+00:00",
      "dateStr": "27 May, 06:00",
      "isNew": false,
      "id": "laj11779861619"
    },
    {
      "title": "Greqi: Flet babai i 19-vjeçares shqiptare: Humba jo engjëllin tim, por jetën time. Vajzën ma futën në kurth, e flakën pasi i bënë gjëra të tmerrshme!",
      "link": "https://www.lajme.al/greqi-flet-babai-i-19-vjecares-shqiptare-humba-jo-engjellin-tim-por-jeten-time-vajzen-ma-futen-ne-kurth-e-flaken-pasi-i-bene-gjera-te-tmerrshme/",
      "description": "Babai i 19-vjeçares që u gjet e pajetë në Kefaloni të Greqisë, foli sonte për mediat greke dhe tha se vajza e tij nuk kishte asnjë lidhje as me lëndë narkotike dhe as me alkool Trishtim i madh ka përfshirë Kefaloninë pas lajmit për vdekjen e 19-vjeçares shqiptare e identifikuar si Mirto, e cila u [&",
      "source": "Lajme.al",
      "category": "politike",
      "date": "2026-04-16T16:54:53+00:00",
      "dateStr": "16 Apr, 16:54",
      "isNew": false,
      "id": "laj21776358493"
    },
    {
      "title": "Gashi: Diasporës parapëlqej t’i them mërgatë, të krijojmë kushtet për rikthimin e tyre në vendlindje",
      "link": "https://www.lajme.al/gashi-diaspores-parapelqej-ti-them-mergate-te-krijojme-kushtet-per-rikthimin-e-tyre-ne-vendlindje/",
      "description": "Kryetari i Kuvendit të Maqedonisë së Veriut, Afrim Gashi, ka theksuar rëndësinë e diasporës dhe nevojën për forcimin e lidhjeve me qytetarët që jetojnë jashtë vendit. Në fjalën e mbajtur në Samitin e IV të Diasporës, Gashi e cilësoi diasporën si një pjesë të pandashme të identitetit, duke u shprehur",
      "source": "Lajme.al",
      "category": "politike",
      "date": "2026-04-14T14:24:35+00:00",
      "dateStr": "14 Apr, 14:24",
      "isNew": false,
      "id": "laj31776176675"
    },
    {
      "title": "Fitër Bajrami – Festë e Besimit, Mirësisë dhe Solidaritetit",
      "link": "https://www.lajme.al/fiter-bajrami-feste-e-besimit-miresise-dhe-solidaritetit/",
      "description": "Me përfundimin e muajit të Ramazanit, besimtarët myslimanë anembanë botës festojnë Fitër Bajramin – një nga festat më të rëndësishme në kalendarin islam. Kjo ditë e shënuar është një moment falënderimi ndaj Zotit, reflektimi për muajin që lamë pas, si dhe një rast për të ndarë gëzim dhe dashuri me t",
      "source": "Lajme.al",
      "category": "politike",
      "date": "2026-03-20T00:03:28+00:00",
      "dateStr": "20 Mar, 00:03",
      "isNew": false,
      "id": "laj41773965008"
    },
    {
      "title": "Albano Bogdo pranon publikisht: “Kam kryer marrëdhënie me një ish-banore të BBV Albania”",
      "link": "https://www.lajme.al/albano-bogdo-pranon-publikisht-kam-kryer-marredhenie-me-nje-ish-banore-te-bbv-albania/",
      "description": "Aktori i njohur i humorit, Albano Bogdo, ka bërë një deklaratë të papritur gjatë pjesëmarrjes së tij në emisionin “Andale”. Gjatë një loje me pyetje provokuese, u lexua pohimi: “Kam bërë marrëdhënie seksuale me një ish-banore që ka qenë në Big Brother Vip Albania”. Pa hezituar, Albano ngriti menjëhe",
      "source": "Lajme.al",
      "category": "politike",
      "date": "2026-02-25T16:28:58+00:00",
      "dateStr": "25 Feb, 16:28",
      "isNew": false,
      "id": "laj51772036938"
    },
    {
      "title": "Del FOTO e rrallë nga arkiva: Ja si dukej Brikena e BBVA para famës",
      "link": "https://www.lajme.al/del-foto-e-rralle-nga-arkiva-ja-si-dukej-brikena-e-bbva-para-fames/",
      "description": "Brikena Selmani është kthyer padyshim në një nga banoret më të komentuara dhe që ka tërhequr vëmendjen në këtë edicion të “Big Brother VIP Albania”, jo vetëm për dinamikat në lojë, por edhe për pamjen e saj. Por, duket se sharmi i modeles daton shumë më herët se dritat e famës televizive. Në rrjetet",
      "source": "Lajme.al",
      "category": "politike",
      "date": "2026-02-25T12:23:06+00:00",
      "dateStr": "25 Feb, 12:23",
      "isNew": false,
      "id": "laj61772022186"
    },
    {
      "title": "LAJM I FUNDIT! Tërmeti shkund Shqipërinë!",
      "link": "https://www.lajme.al/lajm-i-fundit-termeti-shkund-shqiperine/",
      "description": "Elbasani u trondit këtë të martë pasdite nga një tërmet i papritur. Sipas raportimeve të para, lekundjet u ndjenw me intensite. Sipas të dhënave të fundit, një tërmet me magnitudë 4.3 të shkallës Rihter ka goditur Shqipërinë mbrëmjen e sotme, më 24 shkurt 2026. Lëkundjet u regjistruan rreth orës 20:",
      "source": "Lajme.al",
      "category": "politike",
      "date": "2026-02-24T19:16:36+00:00",
      "dateStr": "24 Feb, 19:16",
      "isNew": false,
      "id": "laj71771960596"
    },
    {
      "title": "Diss për Xhensilën? Bes Kallaku publikon këngën e re: “Mes meje dhe teje, dihet kush ishte thëngjilli”",
      "link": "https://www.lajme.al/diss-per-xhensilen-bes-kallaku-publikon-kengen-e-re-mes-meje-dhe-teje-dihet-kush-ishte-thengjilli/",
      "description": "Aktori dhe këngëtari Bes Kallaku ka tërhequr vëmendjen e të gjithë ndjekësve me projektin e tij më të fundit muzikor, një këngë mjaft personale që ngjan me një rrëfim të hapur për ulje-ngritjet e jetës së tij. Menjëherë pas publikimit, rrjeti ka nisur të ziejë nga aludimet se disa prej rreshtave më ",
      "source": "Lajme.al",
      "category": "politike",
      "date": "2026-02-24T19:11:16+00:00",
      "dateStr": "24 Feb, 19:11",
      "isNew": false,
      "id": "laj81771960276"
    },
    {
      "title": "Momenti viral: Takimi i DJ Gimbos me Egli Takon, çfarë u tha mes tyre?",
      "link": "https://www.lajme.al/momenti-viral-takimi-i-dj-gimbos-me-egli-takon-cfare-u-tha-mes-tyre/",
      "description": "Mbrëmjen e djeshme, e ftuar në Big Brother VIP Albania ishte ish-banorja Egli Tako, si pjesë e jurisë së “Miss &#38; Mister Big Brother”. Megjithatë, momenti që mori më shumë vëmendje në rrjet ishte takimi i saj me DJ Gimbon, mikun e ngushtë të Gjestit. Përshëndetja mes tyre ishte e ngrohtë dhe e af",
      "source": "Lajme.al",
      "category": "politike",
      "date": "2026-02-24T16:13:31+00:00",
      "dateStr": "24 Feb, 16:13",
      "isNew": false,
      "id": "laj91771949611"
    }
  ]
}